peer2peer/__init__.py
peer2peer/__main__.py
peer2peer/peer2peer.py
peer2peerchat-0.2.3.dist-info/METADATA
peer2peerchat-0.2.3.dist-info/WHEEL
peer2peerchat-0.2.3.dist-info/entry_points.txt
peer2peerchat-0.2.3.dist-info/top_level.txt
peer2peerchat-0.2.3.dist-info/RECORD
