Metadata-Version: 2.4
Name: peer2peerchat
Version: 0.2.3
Summary: A simple peer-to-peer chat application with clipboard sharing functionality
Home-page: https://github.com/abdullah134/p2pchat
Author: No Name
Classifier: Programming Language :: Python :: 3
Classifier: License :: OSI Approved :: MIT License
Classifier: Operating System :: OS Independent
Classifier: Topic :: Communications :: Chat
Classifier: Topic :: Internet
Requires-Python: >=3.6
Requires-Dist: pyperclip
Dynamic: author
Dynamic: classifier
Dynamic: description
Dynamic: description-content-type
Dynamic: home-page
Dynamic: requires-dist
Dynamic: requires-python
Dynamic: summary
